setup.py
gb_openapi_codec/__init__.py
gb_openapi_codec.egg-info/PKG-INFO
gb_openapi_codec.egg-info/SOURCES.txt
gb_openapi_codec.egg-info/dependency_links.txt
gb_openapi_codec.egg-info/requires.txt
gb_openapi_codec.egg-info/top_level.txt
gb_openapi_codec/__pycache__/__init__.cpython-36.pyc
gb_openapi_codec/python-openapi-codec/.gitignore
gb_openapi_codec/python-openapi-codec/.travis.yml
gb_openapi_codec/python-openapi-codec/LICENSE.md
gb_openapi_codec/python-openapi-codec/MANIFEST.in
gb_openapi_codec/python-openapi-codec/README.md
gb_openapi_codec/python-openapi-codec/requirements.txt
gb_openapi_codec/python-openapi-codec/runtests
gb_openapi_codec/python-openapi-codec/setup.py
gb_openapi_codec/python-openapi-codec/tox.ini
gb_openapi_codec/python-openapi-codec/.git/HEAD
gb_openapi_codec/python-openapi-codec/.git/config
gb_openapi_codec/python-openapi-codec/.git/description
gb_openapi_codec/python-openapi-codec/.git/index
gb_openapi_codec/python-openapi-codec/.git/packed-refs
gb_openapi_codec/python-openapi-codec/.git/hooks/applypatch-msg.sample
gb_openapi_codec/python-openapi-codec/.git/hooks/commit-msg.sample
gb_openapi_codec/python-openapi-codec/.git/hooks/post-update.sample
gb_openapi_codec/python-openapi-codec/.git/hooks/pre-applypatch.sample
gb_openapi_codec/python-openapi-codec/.git/hooks/pre-commit.sample
gb_openapi_codec/python-openapi-codec/.git/hooks/pre-push.sample
gb_openapi_codec/python-openapi-codec/.git/hooks/pre-rebase.sample
gb_openapi_codec/python-openapi-codec/.git/hooks/pre-receive.sample
gb_openapi_codec/python-openapi-codec/.git/hooks/prepare-commit-msg.sample
gb_openapi_codec/python-openapi-codec/.git/hooks/update.sample
gb_openapi_codec/python-openapi-codec/.git/info/exclude
gb_openapi_codec/python-openapi-codec/.git/logs/HEAD
gb_openapi_codec/python-openapi-codec/.git/logs/refs/heads/master
gb_openapi_codec/python-openapi-codec/.git/logs/refs/remotes/origin/HEAD
gb_openapi_codec/python-openapi-codec/.git/objects/pack/pack-5543a1b81bcca1f4fea22e2806c7ef113f1f79df.idx
gb_openapi_codec/python-openapi-codec/.git/objects/pack/pack-5543a1b81bcca1f4fea22e2806c7ef113f1f79df.pack
gb_openapi_codec/python-openapi-codec/.git/refs/heads/master
