Metadata-Version: 1.1
Name: gb-openapi-codec
Version: 1.3.5
Summary: An OpenAPI codec for Core API.
Home-page: http://github.com/crowdcomms/gb-openapi-codec/
Author: Adam Jacquier-Parr
Author-email: ajparr@crowdcomms.com.au
License: BSD
Platform: UNKNOWN
Classifier: Intended Audience :: Developers
Classifier: License :: OSI Approved :: BSD License
Classifier: Operating System :: OS Independent
Classifier: Programming Language :: Python
Classifier: Programming Language :: Python :: 3
